setup.py
bluesadway/__init__.py
bluesadway.egg-info/PKG-INFO
bluesadway.egg-info/SOURCES.txt
bluesadway.egg-info/dependency_links.txt
bluesadway.egg-info/top_level.txt