Metadata-Version: 2.4
Name: bluesadway
Version: 0.1
Summary: bluesadway is for bluesadway api
Home-page: https://sensadway.gov/goi/m5/package
Author: Your Name
Author-email: AbbieKnoblock519@proton.me
Dynamic: author
Dynamic: author-email
Dynamic: home-page
Dynamic: summary
